zb/__init__.py
zb/base.py
zb/cli.py
zb/utils.py
zb/algorithms/__init__.py
zb/algorithms/distant.py
zb/algorithms/fast_cluster.py
zb/algorithms/textrank.py
zb/algorithms/utils.py
zb/crawlers/__init__.py
zb/crawlers/proxies.py
zb/crawlers/utils.py
zb/crawlers/xinshipu.py
zb/dev/__init__.py
zb/dev/decorator.py
zb/dev/keyboard.py
zb/dev/mouse.py
zb/dev/rank.py
zb/dev/sort.py
zb/dev/utils.py
zb/tools/__init__.py
zb/tools/file.py
zb/tools/sms.py
zb/wx/__init__.py
zb/wx/qy.py
zb-0.0.14.dist-info/LICENSE
zb-0.0.14.dist-info/METADATA
zb-0.0.14.dist-info/WHEEL
zb-0.0.14.dist-info/entry_points.txt
zb-0.0.14.dist-info/top_level.txt
zb-0.0.14.dist-info/RECORD
